lintjenkins/__init__.py
lintjenkins/cli.py
lintjenkins/credentials.py
lintjenkins/lintjenkins.py
lintjenkins/template.py
lintjenkins-0.1.13.dist-info/DESCRIPTION.rst
lintjenkins-0.1.13.dist-info/METADATA
lintjenkins-0.1.13.dist-info/RECORD
lintjenkins-0.1.13.dist-info/WHEEL
lintjenkins-0.1.13.dist-info/entry_points.txt
lintjenkins-0.1.13.dist-info/metadata.json
lintjenkins-0.1.13.dist-info/top_level.txt
