Metadata-Version: 2.0
Name: lintjenkins
Version: 0.1.13
Summary: jenkins pylint api.
Home-page: https://github.com/510908220/lintjenkins
Author: westdoorblowcola
Author-email: 510908220@qq.com
License: MIT license
Keywords: lintjenkins
Platform: UNKNOWN
Classifier: Development Status :: 2 - Pre-Alpha
Classifier: Intended Audience :: Developers
Classifier: License :: OSI Approved :: MIT License
Classifier: Natural Language :: English
Classifier: Programming Language :: Python :: 2
Classifier: Programming Language :: Python :: 2.7
Classifier: Programming Language :: Python :: 3
Classifier: Programming Language :: Python :: 3.3
Classifier: Programming Language :: Python :: 3.4
Classifier: Programming Language :: Python :: 3.5
Requires-Dist: Click (>=6.0)
Requires-Dist: jenkinsapi
Requires-Dist: pendulum
Requires-Dist: pyquery
Requires-Dist: python-jenkins
